crawlers/__init__.py
crawlers/chosun_crawler.py
crawlers/crawler.py
crawlers/google_crawler.py
crawlers/kbs_crawler.py
crawlers/khan_crawler.py
crawlers/korea_crawler.py
crawlers/mbc_crawler.py
crawlers/naver_crawler.py
crawlers/sbs_crawler.py
fair_search_packages-0.2.4.dist-info/METADATA
fair_search_packages-0.2.4.dist-info/WHEEL
fair_search_packages-0.2.4.dist-info/top_level.txt
fair_search_packages-0.2.4.dist-info/RECORD
