Metadata-Version: 2.4
Name: fair-search-packages
Version: 0.2.4
Summary: RAG 기반 공평 검색 알고리즘을 위한 전역 Util 함수 모음
Author-email: Kim Seung Min <ak47001@naver.com>
Requires-Python: <3.11,>=3.10
Requires-Dist: fastapi==0.116.1
Requires-Dist: uvicorn[standard]==0.35.0
Requires-Dist: python-dotenv==1.0.1
Requires-Dist: pydantic==2.9.2
Requires-Dist: pydantic-settings==2.2.1
Requires-Dist: PyYAML==6.0.2
Requires-Dist: requests==2.32.3
Requires-Dist: httpx==0.27.2
Requires-Dist: anyio==4.9.0
Requires-Dist: tenacity==8.5.0
Requires-Dist: openai==1.102.0
Requires-Dist: langchain==0.3.27
Requires-Dist: chromadb==1.0.15
Requires-Dist: rank-bm25==0.2.2
Requires-Dist: huggingface-hub==0.34.3
Requires-Dist: transformers==4.53.3
Requires-Dist: safetensors==0.5.3
Requires-Dist: tokenizers==0.21.2
Requires-Dist: numpy==1.26.4
Requires-Dist: scipy==1.13.1
Requires-Dist: scikit-learn==1.5.2
Requires-Dist: pandas==2.3.1
Requires-Dist: datasets==4.3.0
Requires-Dist: pyarrow==21.0.0
Requires-Dist: tqdm==4.67.1
Requires-Dist: regex==2024.11.6
Requires-Dist: PyMySQL==1.1.1
Requires-Dist: SQLAlchemy==2.0.41
